LFSR.v
module LFSR(input clk, rst, output reg [3:0] op);
  always@(posedge clk) begin
    if(rst) op <= 4'hf;
    else op = {op[2:0],(op[3]^op[2])};
  end
endmodule

module TB;
  reg clk, rst;
  wire [3:0]op;
  
  LFSR lfsr1(clk, rst, op);
  
  initial begin
    $monitor("op=%b",op);
    clk = 0; rst = 1;
    #5 rst = 0;
    #50; $finish;
  end
  
  always #2 clk=~clk;
  
  initial begin 
    $dumpfile("dump.vcd"); $dumpvars;
  end
endmodule

dump.vcd
$date
	Tue Jan 16 19:27:16 2024
$end
$version
	Icarus Verilog
$end
$timescale
	1s
$end
$scope module TB $end
$var wire 4 ! op [3:0] $end
$var reg 1 " clk $end
$var reg 1 # rst $end
$scope module lfsr1 $end
$var wire 1 " clk $end
$var wire 1 # rst $end
$var reg 4 $ op [3:0] $end
$upscope $end
$upscope $end
$enddefinitions $end
$comment Show the parameter values. $end
$dumpall
$end
#0
$dumpvars
bx $
1#
0"
bx !
$end
#2
b1111 !
b1111 $
1"
#4
0"
#5
0#
#6
b1110 !
b1110 $
1"
#8
0"
#10
b1100 !
b1100 $
1"
#12
0"
#14
b1000 !
b1000 $
1"
#16
0"
#18
b1 !
b1 $
1"
#20
0"
#22
b10 !
b10 $
1"
#24
0"
#26
b100 !
b100 $
1"
#28
0"
#30
b1001 !
b1001 $
1"
#32
0"
#34
b11 !
b11 $
1"
#36
0"
#38
b110 !
b110 $
1"
#40
0"
#42
b1101 !
b1101 $
1"
#44
0"
#46
b1010 !
b1010 $
1"
#48
0"
#50
b101 !
b101 $
1"
#52
0"
#54
b1011 !
b1011 $
1"
